picorv32_simple.v
module picorv32_simple(
    input clk,
    input reset,
    output reg [31:0] pc,
    output reg [31:0] instruction_count
);

always @(posedge clk or posedge reset)
begin
    if(reset)
    begin
        pc <= 0;
        instruction_count <= 0;
    end
    else
    begin
        pc <= pc + 4;
        instruction_count <= instruction_count + 1;
    end
end

endmodule

testbench.v
`timescale 1ns/1ps

module testbench;

reg clk;
reg reset;

wire [31:0] pc;
wire [31:0] instruction_count;

picorv32_simple uut(
    .clk(clk),
    .reset(reset),
    .pc(pc),
    .instruction_count(instruction_count)
);

always #5 clk = ~clk;

initial
begin
    clk = 0;
    reset = 1;

    #20;
    reset = 0;

    #200;

    $finish;
end

initial
begin
    $dumpfile("picorv32.vcd");
    $dumpvars(0,testbench);
end

initial
begin
    $monitor("Time=%0t PC=%d Instructions=%d",
              $time, pc, instruction_count);
end

endmodule

picorv32.vcd
$date
	Thu Jun 11 19:48:03 2026
$end
$version
	Icarus Verilog
$end
$timescale
	1ps
$end
$scope module testbench $end
$var wire 32 ! pc [31:0] $end
$var wire 32 " instruction_count [31:0] $end
$var reg 1 # clk $end
$var reg 1 $ reset $end
$scope module uut $end
$var wire 1 # clk $end
$var wire 1 $ reset $end
$var reg 32 % instruction_count [31:0] $end
$var reg 32 & pc [31:0] $end
$upscope $end
$upscope $end
$enddefinitions $end
$comment Show the parameter values. $end
$dumpall
$end
#0
$dumpvars
b0 &
b0 %
1$
0#
b0 "
b0 !
$end
#5000
1#
#10000
0#
#15000
1#
#20000
0#
0$
#25000
b1 "
b1 %
b100 !
b100 &
1#
#30000
0#
#35000
b10 "
b10 %
b1000 !
b1000 &
1#
#40000
0#
#45000
b11 "
b11 %
b1100 !
b1100 &
1#
#50000
0#
#55000
b100 "
b100 %
b10000 !
b10000 &
1#
#60000
0#
#65000
b101 "
b101 %
b10100 !
b10100 &
1#
#70000
0#
#75000
b110 "
b110 %
b11000 !
b11000 &
1#
#80000
0#
#85000
b111 "
b111 %
b11100 !
b11100 &
1#
#90000
0#
#95000
b1000 "
b1000 %
b100000 !
b100000 &
1#
#100000
0#
#105000
b1001 "
b1001 %
b100100 !
b100100 &
1#
#110000
0#
#115000
b1010 "
b1010 %
b101000 !
b101000 &
1#
#120000
0#
#125000
b1011 "
b1011 %
b101100 !
b101100 &
1#
#130000
0#
#135000
b1100 "
b1100 %
b110000 !
b110000 &
1#
#140000
0#
#145000
b1101 "
b1101 %
b110100 !
b110100 &
1#
#150000
0#
#155000
b1110 "
b1110 %
b111000 !
b111000 &
1#
#160000
0#
#165000
b1111 "
b1111 %
b111100 !
b111100 &
1#
#170000
0#
#175000
b10000 "
b10000 %
b1000000 !
b1000000 &
1#
#180000
0#
#185000
b10001 "
b10001 %
b1000100 !
b1000100 &
1#
#190000
0#
#195000
b10010 "
b10010 %
b1001000 !
b1001000 &
1#
#200000
0#
#205000
b10011 "
b10011 %
b1001100 !
b1001100 &
1#
#210000
0#
#215000
b10100 "
b10100 %
b1010000 !
b1010000 &
1#
